seed_env/__init__.py
seed_env/cli.py
seed_env/config.py
seed_env/core.py
seed_env/git_utils.py
seed_env/seeder.py
seed_env/utils.py
seed_env/uv_utils.py
seed_env/seeder_configs/jax_seed.yaml
seed_env-0.1.0a3.dist-info/licenses/LICENSE
seed_env-0.1.0a3.dist-info/METADATA
seed_env-0.1.0a3.dist-info/WHEEL
seed_env-0.1.0a3.dist-info/entry_points.txt
seed_env-0.1.0a3.dist-info/top_level.txt
seed_env-0.1.0a3.dist-info/RECORD
