Metadata-Version: 2.4
Name: seed-env
Version: 0.1.0a3
Summary: A CLI tool for environment setup that combines a seeder project with your specific requirements.
Author-email: ml-velocity authors <ml-velocity-team+seed-env@google.com>
License-Expression: Apache-2.0
Project-URL: Homepage, https://github.com/google-ml-infra/actions/tree/main/python_seed_env
Project-URL: Source Code, https://github.com/google-ml-infra/actions/tree/main/python_seed_env
Keywords: cli,environment,seeding,configuration
Classifier: Programming Language :: Python :: 3
Classifier: Programming Language :: Python :: 3 :: Only
Classifier: Intended Audience :: Developers
Requires-Python: >=3.7
License-File: LICENSE
Requires-Dist: uv
Requires-Dist: pyyaml
Requires-Dist: requests
Requires-Dist: toml
Requires-Dist: packaging
Provides-Extra: dev
Requires-Dist: pytest; extra == "dev"
Requires-Dist: pytest-mock; extra == "dev"
Dynamic: license-file
